LAB2/problem3_vending/vending_mealy.v
// CS322M Problem 3: Mealy vending machine with change
// Price=20. Coins: coin[1:0] 01=5, 10=10, 00=idle (11 ignored).
// When total >= 20: dispense=1 for 1 cycle. If total==25: chg5=1 for 1 cycle. Reset total after vend.
module vending_mealy(
input wire clk,
input wire rst, // sync active-high
input wire [1:0] coin, // 01=5, 10=10, 00=idle
output reg dispense, // pulse
output reg chg5 // pulse
);
localparam [1:0] S0 = 2'd0, // total 0
S5 = 2'd1, // total 5
S10= 2'd2, // total 10
S15= 2'd3; // total 15
reg [1:0] state, next_state;

// Decode coin value
wire is5  = (coin == 2'b01);
wire is10 = (coin == 2'b10);
wire idle = (coin == 2'b00) || (coin == 2'b11);

// Next-state logic (combinational)
always @* begin
    next_state = state;
    case (state)
        S0:  begin
                if (is5)      next_state = S5;
                else if (is10)next_state = S10;
             end
        S5:  begin
                if (is5)      next_state = S10;
                else if (is10)next_state = S15;
             end
        S10: begin
                if (is5)      next_state = S15;
                else if (is10)next_state = S0; // vend (20), reset
             end
        S15: begin
                if (is5)      next_state = S0; // vend (20), reset
                else if (is10)next_state = S0; // vend (25), reset (with change)
             end
        default: next_state = S0;
    endcase
end

// State register + Mealy pulses (registered, 1-cycle)
always @(posedge clk) begin
    if (rst) begin
        state <= S0;
        dispense <= 1'b0;
        chg5 <= 1'b0;
    end else begin
        dispense <= 1'b0;
        chg5 <= 1'b0;
        // Vend conditions on observing coin at current state
        case (state)
            S10: if (is10) begin
                      dispense <= 1'b1; // 10+10=20
                  end
            S15: if (is5) begin
                      dispense <= 1'b1; // 15+5=20
                  end else if (is10) begin
                      dispense <= 1'b1; // 15+10=25
                      chg5    <= 1'b1;
                  end
        endcase
        state <= next_state;
    end
end
endmodule

LAB2/problem3_vending/tb_vending_mealy.v
`timescale 1ns/1ps
module tb_vending_mealy;
reg clk = 0, rst = 1;
reg [1:0] coin = 2'b00;
wire dispense, chg5;

vending_mealy dut(.clk(clk), .rst(rst), .coin(coin), .dispense(dispense), .chg5(chg5));

always #5 clk = ~clk; // 100 MHz

task put5; begin
    @(negedge clk); coin = 2'b01;
    @(posedge clk); // sampled
    @(negedge clk); coin = 2'b00;
end endtask

task put10; begin
    @(negedge clk); coin = 2'b10;
    @(posedge clk);
    @(negedge clk); coin = 2'b00;
end endtask

initial begin
    $dumpfile("dump.vcd");
    $dumpvars(0, tb_vending_mealy);
    repeat (3) @(posedge clk);
    rst = 1'b0;

    // 10+10 => vend
    put10(); if (dispense) $display("Unexpected vend early");
    put10(); @(posedge clk);
    if (dispense && !chg5) $display("%0t ns: VEND (20)", $time);

    // 5+5+10 => vend
    put5(); put5(); put10(); @(posedge clk);
    if (dispense && !chg5) $display("%0t ns: VEND (20)", $time);

    // 10+5+10 => vend + chg5
    put10(); put5(); put10(); @(posedge clk);
    if (dispense && chg5) $display("%0t ns: VEND (25) + CHANGE 5", $time);

    // Idle robustness
    @(negedge clk); coin = 2'b11; @(posedge clk); @(negedge clk); coin = 2'b00;

    #50 $finish;
end

endmodule

LAB2/problem3_vending/waves/dump.vcd
$date
	Fri Aug 15 11:30:55 2025
$end
$version
	Icarus Verilog
$end
$timescale
	1ps
$end
$scope module tb_vending_mealy $end
$var wire 1 ! dispense $end
$var wire 1 " chg5 $end
$var reg 1 # clk $end
$var reg 2 $ coin [1:0] $end
$var reg 1 % rst $end
$scope module dut $end
$var wire 1 # clk $end
$var wire 2 & coin [1:0] $end
$var wire 1 ' idle $end
$var wire 1 % rst $end
$var wire 1 ( is5 $end
$var wire 1 ) is10 $end
$var parameter 2 * S0 $end
$var parameter 2 + S10 $end
$var parameter 2 , S15 $end
$var parameter 2 - S5 $end
$var reg 1 " chg5 $end
$var reg 1 ! dispense $end
$var reg 2 . next_state [1:0] $end
$var reg 2 / state [1:0] $end
$upscope $end
$scope task put10 $end
$upscope $end
$scope task put5 $end
$upscope $end
$upscope $end
$enddefinitions $end
$comment Show the parameter values. $end
$dumpall
b1 -
b11 ,
b10 +
b0 *
$end
#0
$dumpvars
bx /
b0 .
0)
0(
1'
b0 &
1%
b0 $
0#
x"
x!
$end
#5000
0"
0!
b0 /
1#
#10000
0#
#15000
1#
#20000
0#
#25000
0%
1#
#30000
b10 .
0'
1)
b10 $
b10 &
0#
#35000
b0 .
b10 /
1#
#40000
b10 .
1'
0)
b0 $
b0 &
0#
#45000
1#
#50000
b0 .
0'
1)
b10 $
b10 &
0#
#55000
b10 .
b0 /
1!
1#
#60000
b0 .
1'
0)
b0 $
b0 &
0#
#65000
0!
1#
#70000
b1 .
0'
1(
b1 $
b1 &
0#
#75000
b10 .
b1 /
1#
#80000
b1 .
1'
0(
b0 $
b0 &
0#
#85000
1#
#90000
b10 .
0'
1(
b1 $
b1 &
0#
#95000
b11 .
b10 /
1#
#100000
b10 .
1'
0(
b0 $
b0 &
0#
#105000
1#
#110000
b0 .
0'
1)
b10 $
b10 &
0#
#115000
b10 .
b0 /
1!
1#
#120000
b0 .
1'
0)
b0 $
b0 &
0#
#125000
0!
1#
#130000
b10 .
0'
1)
b10 $
b10 &
0#
#135000
b0 .
b10 /
1#
#140000
b10 .
1'
0)
b0 $
b0 &
0#
#145000
1#
#150000
b11 .
0'
1(
b1 $
b1 &
0#
#155000
b0 .
b11 /
1#
#160000
b11 .
1'
0(
b0 $
b0 &
0#
#165000
1#
#170000
b0 .
0'
1)
b10 $
b10 &
0#
#175000
b10 .
b0 /
1"
1!
1#
#180000
b0 .
1'
0)
b0 $
b0 &
0#
#185000
0"
0!
1#
#190000
b11 $
b11 &
0#
#195000
1#
#200000
b0 $
b0 &
0#
