LAB2/problem1_seqdet/seq_detect_mealy.v
module seq_detect_mealy(
    input  wire clk,
    input  wire rst,   // sync active-high
    input  wire din,   // serial input bit per clock
    output reg  y      // 1-cycle pulse at detection
);
    localparam [1:0] S0   = 2'd0, // no match
                     S1   = 2'd1, // seen '1'
                     S11  = 2'd2, // seen '11'
                     S110 = 2'd3; // seen '110'
    reg [1:0] state, next_state;

    // Next-state logic
    always @* begin
        case (state)
            S0:    next_state = din ? S1   : S0;
            S1:    next_state = din ? S11  : S0;
            S11:   next_state = din ? S11  : S110;
            S110:  next_state = din ? S1   : S0;   // on '1' we also fire output
            default: next_state = S0;
        endcase
    end

    // State register
    always @(posedge clk) begin
        if (rst) begin
            state <= S0;
            y <= 1'b0;
        end else begin
            y <= 1'b0;
            // Pulse when (pattern 1101 complete)
            if (state == S110 && din) y <= 1'b1;
            state <= next_state;
        end
    end
endmodule

LAB2/problem1_seqdet/tb_seq_detect_mealy.v
`timescale 1ns/1ps
module tb_seq_detect_mealy;
    reg clk = 0, rst = 1, din = 0;
    wire y;
    reg [10:0] stream;   // <-- move here (module scope)

    seq_detect_mealy dut(.clk(clk), .rst(rst), .din(din), .y(y));

    always #5 clk = ~clk;

    task send(input b);  // 1-bit input
        begin
            @(negedge clk);
            din = b;
            @(posedge clk);
        end
    endtask

    integer i, detects;
    initial begin
        $dumpfile("dump.vcd");
        $dumpvars(0, tb_seq_detect_mealy);

        repeat (3) @(posedge clk);
        rst = 1'b0;

        // Stream bits
        stream[0]=1; stream[1]=1; stream[2]=0; stream[3]=1;
        stream[4]=1; stream[5]=0; stream[6]=1;
        stream[7]=1; stream[8]=1; stream[9]=0; stream[10]=1;

        detects = 0;
        for (i=0; i<=10; i=i+1) begin
            send(stream[i]);
            if (y) begin
                $display("%0t ns: DETECT at index %0d", $time, i);
                detects = detects + 1;
            end
        end

        // Verilog random
        repeat (10) begin
            send($random & 1);
            if (y) begin
                $display("%0t ns: DETECT (random)", $time);
                detects = detects + 1;
            end
        end

        $display("Total detects: %0d", detects);
        #20 $finish;
    end
endmodule

LAB2/problem1_seqdet/waves/dump.vcd
$date
	Fri Aug 15 11:30:31 2025
$end
$version
	Icarus Verilog
$end
$timescale
	1ps
$end
$scope module tb_seq_detect_mealy $end
$var wire 1 ! y $end
$var reg 1 " clk $end
$var reg 1 # din $end
$var reg 1 $ rst $end
$var reg 11 % stream [10:0] $end
$var integer 32 & detects [31:0] $end
$var integer 32 ' i [31:0] $end
$scope module dut $end
$var wire 1 " clk $end
$var wire 1 # din $end
$var wire 1 $ rst $end
$var parameter 2 ( S0 $end
$var parameter 2 ) S1 $end
$var parameter 2 * S11 $end
$var parameter 2 + S110 $end
$var reg 2 , next_state [1:0] $end
$var reg 2 - state [1:0] $end
$var reg 1 ! y $end
$upscope $end
$scope task send $end
$var reg 1 . b $end
$upscope $end
$upscope $end
$enddefinitions $end
$comment Show the parameter values. $end
$dumpall
b11 +
b10 *
b1 )
b0 (
$end
#0
$dumpvars
x.
bx -
b0 ,
bx '
bx &
bx %
1$
0#
0"
x!
$end
#5000
0!
b0 -
1"
#10000
0"
#15000
1"
#20000
0"
#25000
1.
b0 '
b0 &
b10111011011 %
0$
1"
#30000
b1 ,
1#
0"
#35000
b10 ,
b1 -
b1 '
1"
#40000
0"
#45000
b10 -
0.
b10 '
1"
#50000
b11 ,
0#
0"
#55000
b0 ,
b11 -
1.
b11 '
1"
#60000
b1 ,
1#
0"
#65000
b10 ,
b1 -
1!
b100 '
1"
#70000
0"
#75000
b10 -
0!
0.
b101 '
b1 &
1"
#80000
b11 ,
0#
0"
#85000
b0 ,
b11 -
1.
b110 '
1"
#90000
b1 ,
1#
0"
#95000
b10 ,
b1 -
1!
b111 '
1"
#100000
0"
#105000
b10 -
0!
b1000 '
b10 &
1"
#110000
0"
#115000
0.
b1001 '
1"
#120000
b11 ,
0#
0"
#125000
b0 ,
b11 -
1.
b1010 '
1"
#130000
b1 ,
1#
0"
#135000
b10 ,
b1 -
1!
0.
b1011 '
1"
#140000
b0 ,
0#
0"
#145000
b0 -
0!
1.
b11 &
1"
#150000
b1 ,
1#
0"
#155000
b10 ,
b1 -
1"
#160000
0"
#165000
b10 -
1"
#170000
0"
#175000
1"
#180000
0"
#185000
1"
#190000
0"
#195000
1"
#200000
0"
#205000
0.
1"
#210000
b11 ,
0#
0"
#215000
b0 ,
b11 -
1.
1"
#220000
b1 ,
1#
0"
#225000
b10 ,
b1 -
1!
1"
#230000
0"
#235000
b10 -
0!
b100 &
1"
