LAB2/problem4_link/slave_fsm.v
// CS322M Problem 4: Slave FSM
// On req high: latch data_in, assert ack for >=2 cycles; after 2 cycles and once req is low, deassert ack.
module slave_fsm(
input wire clk,
input wire rst, // sync
input wire req,
input wire [7:0] data_in,
output reg ack,
output reg [7:0] last_byte
);
localparam [1:0] WAIT_REQ = 2'd0,
ASSERT_ACK = 2'd1,
AFTER_2 = 2'd2,
DROP_ACK = 2'd3;

reg [1:0] state, next_state;
reg [1:0] hold_cnt; // count 0..1 (2 cycles)

// Next-state logic
always @* begin
    next_state = state;
    case (state)
        WAIT_REQ:   if (req) next_state = ASSERT_ACK;
        ASSERT_ACK: if (hold_cnt == 2'd1) next_state = AFTER_2;
        AFTER_2:    if (!req) next_state = DROP_ACK; // wait for master to drop req
        DROP_ACK:   next_state = WAIT_REQ;
        default:    next_state = WAIT_REQ;
    endcase
end

// Registers & outputs
always @(posedge clk) begin
    if (rst) begin
        state <= WAIT_REQ;
        hold_cnt <= 2'd0;
        ack <= 1'b0;
        last_byte <= 8'h00;
    end else begin
        state <= next_state;
        case (state)
            WAIT_REQ: begin
                ack <= 1'b0;
                hold_cnt <= 2'd0;
                if (req) begin
                    last_byte <= data_in; // latch when request observed
                end
            end
            ASSERT_ACK: begin
                ack <= 1'b1;
                hold_cnt <= hold_cnt + 1'b1; // will count 0,1 for 2 cycles
            end
            AFTER_2: begin
                ack <= 1'b1; // keep high until req is low
            end
            DROP_ACK: begin
                ack <= 1'b0;
            end
        endcase
    end
end

endmodule

LAB2/problem4_link/master_fsm.v
// CS322M Problem 4: Master FSM (4-byte burst A0..A3)
// 4-phase handshake: Master drives data, raises req; waits ack; drops req; waits ack low; repeat.
// 'done' pulses 1 cycle after the 4th byte handshake completes.
module master_fsm(
input wire clk,
input wire rst, // sync
input wire ack,
output reg req,
output reg [7:0] data,
output reg done // 1-cycle pulse when burst completes
);
localparam [2:0] IDLE=3'd0, REQ_H=3'd1, WAIT_ACK=3'd2, DROP_REQ=3'd3, WAIT_ACK_LO=3'd4, DONE=3'd5;

reg [2:0] state, next_state;
reg [1:0] idx; // 0..3

// Next state
always @* begin
    next_state = state;
    case (state)
        IDLE:       next_state = REQ_H;
        REQ_H:      next_state = ack ? WAIT_ACK : REQ_H;
        WAIT_ACK:   next_state = DROP_REQ; // ack just observed; keep req high this cycle
        DROP_REQ:   next_state = WAIT_ACK_LO;
        WAIT_ACK_LO:begin
                        if (!ack) begin
                            if (idx == 2'd3) next_state = DONE;
                            else             next_state = REQ_H;
                        end
                    end
        DONE:       next_state = DONE;
        default:    next_state = IDLE;
    endcase
end

// Output & registers
always @(posedge clk) begin
    if (rst) begin
        state <= IDLE;
        idx   <= 2'd0;
        req   <= 1'b0;
        data  <= 8'hA0;
        done  <= 1'b0;
    end else begin
        done <= 1'b0; // default
        state <= next_state;

        case (state)
            IDLE: begin
                // load first byte
                idx  <= 2'd0;
                data <= 8'hA0;
                req  <= 1'b0;
            end
            REQ_H: begin
                req <= 1'b1; // drive data & req high until ack
            end
            WAIT_ACK: begin
                req <= 1'b1; // still high for one cycle to allow slave to see it
            end
            DROP_REQ: begin
                req <= 1'b0;
            end
            WAIT_ACK_LO: begin
                if (!ack) begin
                    // prepare next byte
                    if (idx != 2'd3) begin
                        idx  <= idx + 1'b1;
                        data <= 8'hA0 + {6'd0, idx} + 8'h01; // A0, A1, A2, A3
                        // Note: 'data' advances at the moment we schedule next REQ_H
                    end
                end
            end
            DONE: begin
                done <= 1'b1; // single-cycle pulse
                req  <= 1'b0;
            end
        endcase
    end
end

endmodule

LAB2/problem4_link/link_top.v
// CS322M Problem 4: Top-level connecting master and slave
module link_top(
input wire clk,
input wire rst,
output wire done
);
wire req, ack;
wire [7:0] data_bus;
master_fsm u_master(.clk(clk), .rst(rst), .ack(ack), .req(req), .data(data_bus), .done(done));
slave_fsm  u_slave (.clk(clk), .rst(rst), .req(req), .data_in(data_bus), .ack(ack), .last_byte());
endmodule

LAB2/problem4_link/tb_link_top.v
// CS322M Problem 4 TB: Master–Slave 4-phase handshake
`timescale 1ns/1ps
module tb_link_top;
reg clk = 0, rst = 1;
wire done;
link_top dut(.clk(clk), .rst(rst), .done(done));

always #5 clk = ~clk; // 100 MHz

initial begin
    $dumpfile("dump.vcd");
    $dumpvars(0, tb_link_top);
    repeat (3) @(posedge clk);
    rst = 0;

    // Monitor key handshake signals
    $display("time  req ack data   done");
    forever begin
        @(posedge clk);
        $display("%0t  %0b   %0b   0x%0h   %0b",
                 $time, dut.u_master.req, dut.u_slave.ack, dut.u_master.data, done);
        if (done) begin
            // give a few more cycles for visibility
            repeat (2) @(posedge clk);
            $finish;
        end
    end
end
endmodule

LAB2/problem4_link/waves/dump.vcd
$date
	Fri Aug 15 11:31:21 2025
$end
$version
	Icarus Verilog
$end
$timescale
	1ps
$end
$scope module tb_link_top $end
$var wire 1 ! done $end
$var reg 1 " clk $end
$var reg 1 # rst $end
$scope module dut $end
$var wire 1 " clk $end
$var wire 1 # rst $end
$var wire 1 $ req $end
$var wire 1 ! done $end
$var wire 8 % data_bus [7:0] $end
$var wire 1 & ack $end
$scope module u_master $end
$var wire 1 " clk $end
$var wire 1 # rst $end
$var wire 1 & ack $end
$var parameter 3 ' DONE $end
$var parameter 3 ( DROP_REQ $end
$var parameter 3 ) IDLE $end
$var parameter 3 * REQ_H $end
$var parameter 3 + WAIT_ACK $end
$var parameter 3 , WAIT_ACK_LO $end
$var reg 8 - data [7:0] $end
$var reg 1 ! done $end
$var reg 2 . idx [1:0] $end
$var reg 3 / next_state [2:0] $end
$var reg 1 $ req $end
$var reg 3 0 state [2:0] $end
$upscope $end
$scope module u_slave $end
$var wire 1 " clk $end
$var wire 8 1 data_in [7:0] $end
$var wire 1 $ req $end
$var wire 1 # rst $end
$var parameter 2 2 AFTER_2 $end
$var parameter 2 3 ASSERT_ACK $end
$var parameter 2 4 DROP_ACK $end
$var parameter 2 5 WAIT_REQ $end
$var reg 1 & ack $end
$var reg 2 6 hold_cnt [1:0] $end
$var reg 8 7 last_byte [7:0] $end
$var reg 2 8 next_state [1:0] $end
$var reg 2 9 state [1:0] $end
$upscope $end
$upscope $end
$upscope $end
$enddefinitions $end
$comment Show the parameter values. $end
$dumpall
b0 5
b11 4
b1 3
b10 2
b100 ,
b10 +
b1 *
b0 )
b11 (
b101 '
$end
#0
$dumpvars
bx 9
bx 8
bx 7
bx 6
bx 1
bx 0
bx /
bx .
bx -
x&
bx %
x$
1#
0"
x!
$end
#5000
b1 /
b0 8
0!
b10100000 %
b10100000 -
b10100000 1
0$
b0 .
b0 0
b0 7
0&
b0 6
b0 9
1"
#10000
0"
#15000
1"
#20000
0"
#25000
b1 0
0#
1"
#30000
0"
#35000
b1 8
1$
1"
#40000
0"
#45000
b10100000 7
b1 9
1"
#50000
0"
#55000
b10 8
b10 /
b1 6
1&
1"
#60000
0"
#65000
b11 /
b10 0
b10 6
b10 9
1"
#70000
0"
#75000
b100 /
b11 0
1"
#80000
0"
#85000
b11 8
0$
b100 0
1"
#90000
0"
#95000
b0 8
b11 9
1"
#100000
0"
#105000
b1 /
0&
b0 9
1"
#110000
0"
#115000
b0 6
b10100001 %
b10100001 -
b10100001 1
b1 .
b1 0
1"
#120000
0"
#125000
b1 8
1$
1"
#130000
0"
#135000
b10100001 7
b1 9
1"
#140000
0"
#145000
b10 8
b10 /
b1 6
1&
1"
#150000
0"
#155000
b11 /
b10 6
b10 9
b10 0
1"
#160000
0"
#165000
b100 /
b11 0
1"
#170000
0"
#175000
b11 8
0$
b100 0
1"
#180000
0"
#185000
b0 8
b11 9
1"
#190000
0"
#195000
b1 /
0&
b0 9
1"
#200000
0"
#205000
b10100010 %
b10100010 -
b10100010 1
b10 .
b1 0
b0 6
1"
#210000
0"
#215000
b1 8
1$
1"
#220000
0"
#225000
b10100010 7
b1 9
1"
#230000
0"
#235000
b10 8
b10 /
b1 6
1&
1"
#240000
0"
#245000
b11 /
b10 0
b10 6
b10 9
1"
#250000
0"
#255000
b100 /
b11 0
1"
#260000
0"
#265000
b11 8
0$
b100 0
1"
#270000
0"
#275000
b0 8
b11 9
1"
#280000
0"
#285000
b1 /
0&
b0 9
1"
#290000
0"
#295000
b0 6
b10100011 %
b10100011 -
b10100011 1
b11 .
b1 0
1"
#300000
0"
#305000
b1 8
1$
1"
#310000
0"
#315000
b10100011 7
b1 9
1"
#320000
0"
#325000
b10 8
b10 /
b1 6
1&
1"
#330000
0"
#335000
b11 /
b10 6
b10 9
b10 0
1"
#340000
0"
#345000
b100 /
b11 0
1"
#350000
0"
#355000
b11 8
0$
b100 0
1"
#360000
0"
#365000
b0 8
b11 9
1"
#370000
0"
#375000
b101 /
0&
b0 9
1"
#380000
0"
#385000
b101 0
b0 6
1"
#390000
0"
#395000
1!
1"
#400000
0"
#405000
1!
1"
#410000
0"
#415000
1!
1"
#420000
0"
#425000
1!
1"
